modem_cmd-1.0.0.data/scripts/modem-cmd
modem_cmd-1.0.0.dist-info/DESCRIPTION.rst
modem_cmd-1.0.0.dist-info/METADATA
modem_cmd-1.0.0.dist-info/RECORD
modem_cmd-1.0.0.dist-info/WHEEL
modem_cmd-1.0.0.dist-info/metadata.json
modem_cmd-1.0.0.dist-info/top_level.txt
modemcmd/__init__.py
