Metadata-Version: 2.0
Name: modem-cmd
Version: 1.0.0
Summary: Send arbitrary AT commands to your modem
Home-page: https://github.com/imZack/modem-cmd
Author: YuLun Shih
Author-email: shih@yulun.me
License: MIT
Download-URL: https://github.com/imZack/modem-cmd/archive/1.0.0.tar.gz
Keywords: modem,at commands,serial
Platform: UNKNOWN
Classifier: Environment :: Console
Classifier: Intended Audience :: Developers
Classifier: Intended Audience :: Telecommunications Industry
Classifier: Development Status :: 3 - Alpha
Classifier: License :: OSI Approved :: MIT License
Classifier: Programming Language :: Python :: 2.6
Classifier: Programming Language :: Python :: 2.7
Classifier: Topic :: Communications :: Telephony
Classifier: Topic :: Software Development :: Libraries :: Python Modules
Classifier: Topic :: System :: Hardware
Classifier: Topic :: Terminals :: Serial
Classifier: Topic :: Utilities
Classifier: Operating System :: OS Independent
Requires-Dist: pyserial (>=2.6)
